dataride/__init__.py
dataride/application/__init__.py
dataride/application/application.py
dataride/assets/__init__.py
dataride/assets/asset.py
dataride/assets/asset_action_required.py
dataride/assets/asset_airflow_local.py
dataride/assets/asset_mageai_local.py
dataride/assets/data.py
dataride/configs/__init__.py
dataride/configs/abstracts/__init__.py
dataride/configs/abstracts/to_dict.py
dataride/configs/elements/__init__.py
dataride/configs/elements/environment.py
dataride/configs/elements/module.py
dataride/configs/elements/resource.py
dataride/configs/elements/variable.py
dataride/configs/infra.py
dataride/dataride.py
dataride/utils/__init__.py
dataride/utils/utils.py
dataride-0.2.3.dist-info/entry_points.txt
dataride-0.2.3.dist-info/LICENSE
dataride-0.2.3.dist-info/WHEEL
dataride-0.2.3.dist-info/METADATA
dataride-0.2.3.dist-info/RECORD
