Metadata-Version: 2.1
Name: dataride
Version: 0.2.3
Summary: Lightning-fast data platform setup for small/medium projects & PoCs
License: MIT
Keywords: data,platform,cloud,infrastructure,terraform,python
Author: Mateusz Polakowski
Author-email: mateusz.polakowski.ds@gmail.com
Requires-Python: >=3.8,<4.0
Classifier: License :: OSI Approved :: MIT License
Classifier: Programming Language :: Python
Classifier: Programming Language :: Python :: 3
Classifier: Programming Language :: Python :: 3.8
Classifier: Programming Language :: Python :: 3.9
Classifier: Programming Language :: Python :: 3.10
Classifier: Programming Language :: Python :: 3
Classifier: Programming Language :: Python :: 3.10
Classifier: Programming Language :: Python :: 3.8
Classifier: Programming Language :: Python :: 3.9
Requires-Dist: Jinja2 (>=3.1.2,<4.0.0)
Requires-Dist: PyYAML (>=6.0,<7.0)
Requires-Dist: click (>=8.1.3,<9.0.0)
Requires-Dist: pyhcl (>=0.4.4,<0.5.0)
Requires-Dist: python-hcl2 (>=3.0.5,<4.0.0)
Requires-Dist: toml (>=0.10.2,<0.11.0)
